{
  "entrypoints": [
    "main"
  ],
  "origins": {
    "237": [
      237
    ],
    "341": [
      540,
      341
    ],
    "489": [
      741,
      489
    ],
    "540": [
      341,
      540
    ],
    "741": [
      489,
      741
    ],
    "17896441": [
      869,
      401
    ],
    "main": [
      354,
      869,
      792
    ],
    "runtime~main": [
      792,
      869,
      354
    ],
    "0e384e19": [
      976
    ],
    "138e0e15": [
      921
    ],
    "1a4e3797": [
      869,
      138
    ],
    "5e95c892": [
      647
    ],
    "7a96ca3d": [
      271
    ],
    "9f1a7113": [
      888
    ],
    "a7bd4aaa": [
      98
    ],
    "a94703ab": [
      869,
      48
    ],
    "aba21aa0": [
      742
    ],
    "styles": [
      48,
      138,
      354,
      401,
      792,
      869
    ]
  },
  "assets": {
    "48": {
      "js": [
        {
          "file": "assets/js/a94703ab.506e06d2.js",
          "hash": "a199f2c15b3980e8",
          "publicPath": "/newtest/assets/js/a94703ab.506e06d2.js"
        }
      ]
    },
    "98": {
      "js": [
        {
          "file": "assets/js/a7bd4aaa.6cc331c9.js",
          "hash": "e66261aa671a00fd",
          "publicPath": "/newtest/assets/js/a7bd4aaa.6cc331c9.js"
        }
      ]
    },
    "138": {
      "js": [
        {
          "file": "assets/js/1a4e3797.78c842cf.js",
          "hash": "9304f9aa2ece2b10",
          "publicPath": "/newtest/assets/js/1a4e3797.78c842cf.js"
        }
      ]
    },
    "237": {
      "js": [
        {
          "file": "assets/js/237.a94d54fa.js",
          "hash": "f14fda8ffbc6de5c",
          "publicPath": "/newtest/assets/js/237.a94d54fa.js"
        }
      ]
    },
    "271": {
      "js": [
        {
          "file": "assets/js/7a96ca3d.6c8131de.js",
          "hash": "afe37c94ec92c90f",
          "publicPath": "/newtest/assets/js/7a96ca3d.6c8131de.js"
        }
      ]
    },
    "341": {
      "js": [
        {
          "file": "assets/js/341.b45f8693.js",
          "hash": "167fd33fed431616",
          "publicPath": "/newtest/assets/js/341.b45f8693.js"
        }
      ]
    },
    "354": {
      "js": [
        {
          "file": "assets/js/runtime~main.9a219509.js",
          "hash": "190f368e4fc6d4da",
          "publicPath": "/newtest/assets/js/runtime~main.9a219509.js"
        }
      ]
    },
    "401": {
      "js": [
        {
          "file": "assets/js/17896441.1232d0d0.js",
          "hash": "07e31f88365a267e",
          "publicPath": "/newtest/assets/js/17896441.1232d0d0.js"
        }
      ]
    },
    "489": {
      "js": [
        {
          "file": "assets/js/489.073d6b3a.js",
          "hash": "4af567c9d6c39c34",
          "publicPath": "/newtest/assets/js/489.073d6b3a.js"
        }
      ]
    },
    "540": {
      "js": [
        {
          "file": "assets/js/540.4c356dc6.js",
          "hash": "be54aa0751c16d19",
          "publicPath": "/newtest/assets/js/540.4c356dc6.js"
        }
      ]
    },
    "647": {
      "js": [
        {
          "file": "assets/js/5e95c892.9c0102f3.js",
          "hash": "595a91317050929c",
          "publicPath": "/newtest/assets/js/5e95c892.9c0102f3.js"
        }
      ]
    },
    "741": {
      "js": [
        {
          "file": "assets/js/741.839af56c.js",
          "hash": "c9a7de6714c0a2fe",
          "publicPath": "/newtest/assets/js/741.839af56c.js"
        }
      ]
    },
    "742": {
      "js": [
        {
          "file": "assets/js/aba21aa0.6ad32bfd.js",
          "hash": "5b7b006629e43186",
          "publicPath": "/newtest/assets/js/aba21aa0.6ad32bfd.js"
        }
      ]
    },
    "792": {
      "js": [
        {
          "file": "assets/js/main.936ee6d8.js",
          "hash": "2b5966fdae334d4b",
          "publicPath": "/newtest/assets/js/main.936ee6d8.js"
        }
      ]
    },
    "869": {
      "css": [
        {
          "file": "assets/css/styles.8cc9f40d.css",
          "hash": "11002ee020ab0675",
          "publicPath": "/newtest/assets/css/styles.8cc9f40d.css"
        }
      ]
    },
    "888": {
      "js": [
        {
          "file": "assets/js/9f1a7113.aaa9a91a.js",
          "hash": "3dd9c5b854f60a97",
          "publicPath": "/newtest/assets/js/9f1a7113.aaa9a91a.js"
        }
      ]
    },
    "921": {
      "js": [
        {
          "file": "assets/js/138e0e15.f98846d6.js",
          "hash": "ca572c8442456a09",
          "publicPath": "/newtest/assets/js/138e0e15.f98846d6.js"
        }
      ]
    },
    "976": {
      "js": [
        {
          "file": "assets/js/0e384e19.1f5df90a.js",
          "hash": "e6888962b61f715f",
          "publicPath": "/newtest/assets/js/0e384e19.1f5df90a.js"
        }
      ]
    }
  }
}